{
    "Configurations":{
        "NameSpace":"Web",
        "Registered":[
            {
                "Id":"testServlet",
                "Class":"Web::TestServlet",
                "Interface":"Magic::NetWork::Http::IHttpServlet",
                "IncludePath":"WebServer/TestServlet.h",
                "Dependencies":[],
                "FunctionPropertys":[]
            }
        ],
        "Initialize":[
            {
                "Id":"testServlet",
                "InvokeFunctions":{
                    "addRoute":["\"/test\"","&Web::TestServlet::test"]
                }
            }
        ],
        "Constructor":{
            "Name":"Initialize",
            "WithParameter": true
        }
    }
}
